[
    {
        "id": 1801,
        "target": "Me gusta jugar al fútbol los fines de semana con mis amigos.",
        "english": "I like to play soccer on weekends with my friends.",
        "audio": "",
        "interval": 0,
        "ease": 2.5,
        "due": 0
    },
    {
        "id": 1802,
        "target": "El baloncesto y el voleibol son deportes de equipo muy populares.",
        "english": "Basketball and volleyball are very popular team sports.",
        "audio": "",
        "interval": 0,
        "ease": 2.5,
        "due": 0
    },
    {
        "id": 1803,
        "target": "Nado en la piscina tres veces por semana para mantenerme en forma.",
        "english": "I swim in the pool three times a week to stay in shape.",
        "audio": "",
        "interval": 0,
        "ease": 2.5,
        "due": 0
    },
    {
        "id": 1804,
        "target": "Salgo a correr por el parque todas las mañanas antes de ir al trabajo.",
        "english": "I go running in the park every morning before going to work.",
        "audio": "",
        "interval": 0,
        "ease": 2.5,
        "due": 0
    },
    {
        "id": 1805,
        "target": "El tenista ganó el partido en tres sets muy reñidos.",
        "english": "The tennis player won the match in three very close sets.",
        "audio": "",
        "interval": 0,
        "ease": 2.5,
        "due": 0,
        "grammar": "\"Me encanta jugar al fútbol los fines de semana\" — \"jugar a\" + sport: \"jugar al fútbol, jugar al tenis.\" \"Al\" = a + el. \"Encantar\" like gustar."
    },
    {
        "id": 1806,
        "target": "Aprendí a esquiar cuando tenía diez años en los Pirineos.",
        "english": "I learned to ski when I was ten years old in the Pyrenees.",
        "audio": "",
        "interval": 0,
        "ease": 2.5,
        "due": 0
    },
    {
        "id": 1807,
        "target": "El ciclismo es mi deporte favorito; tengo una bicicleta de montaña.",
        "english": "Cycling is my favorite sport; I have a mountain bike.",
        "audio": "",
        "interval": 0,
        "ease": 2.5,
        "due": 0
    },
    {
        "id": 1808,
        "target": "El equipo local empató dos a dos en el último minuto del partido.",
        "english": "The local team tied two to two in the last minute of the match.",
        "audio": "",
        "interval": 0,
        "ease": 2.5,
        "due": 0
    },
    {
        "id": 1809,
        "target": "El árbitro le sacó tarjeta roja al jugador por una falta grave.",
        "english": "The referee showed the player a red card for a serious foul.",
        "audio": "",
        "interval": 0,
        "ease": 2.5,
        "due": 0
    },
    {
        "id": 1810,
        "target": "Los atletas entrenan durante años para competir en los Juegos Olímpicos.",
        "english": "Athletes train for years to compete in the Olympic Games.",
        "audio": "",
        "interval": 0,
        "ease": 2.5,
        "due": 0,
        "grammar": "\"Llevo dos años practicando yoga\" — \"llevar\" + time + gerund = have been doing for. \"Practicar\" — no preposition before the activity."
    },
    {
        "id": 1811,
        "target": "Hicimos senderismo por una ruta preciosa con vistas al valle.",
        "english": "We went hiking along a beautiful trail with views of the valley.",
        "audio": "",
        "interval": 0,
        "ease": 2.5,
        "due": 0
    },
    {
        "id": 1812,
        "target": "La escalada en roca requiere fuerza, técnica y concentración.",
        "english": "Rock climbing requires strength, technique, and concentration.",
        "audio": "",
        "interval": 0,
        "ease": 2.5,
        "due": 0
    },
    {
        "id": 1813,
        "target": "Practico yoga todas las mañanas para relajarme y estirar los músculos.",
        "english": "I practice yoga every morning to relax and stretch my muscles.",
        "audio": "",
        "interval": 0,
        "ease": 2.5,
        "due": 0
    },
    {
        "id": 1814,
        "target": "El estadio estaba lleno de aficionados que animaban a su equipo.",
        "english": "The stadium was full of fans cheering for their team.",
        "audio": "",
        "interval": 0,
        "ease": 2.5,
        "due": 0
    },
    {
        "id": 1815,
        "target": "El campeonato mundial de atletismo se celebra cada dos años.",
        "english": "The world athletics championship is held every two years.",
        "audio": "",
        "interval": 0,
        "ease": 2.5,
        "due": 0,
        "grammar": "\"Si hiciera mejor tiempo, saldríamos a correr\" — unreal conditional: si + imperfect subjunctive → conditional. \"Saldríamos\" from \"salir\" (irregular conditional stem: saldr-)."
    },
    {
        "id": 1816,
        "target": "Perdieron el partido porque el portero no pudo parar el penalti.",
        "english": "They lost the match because the goalkeeper couldn't stop the penalty.",
        "audio": "",
        "interval": 0,
        "ease": 2.5,
        "due": 0
    },
    {
        "id": 1817,
        "target": "El entrenador diseñó una estrategia para ganar la final del torneo.",
        "english": "The coach designed a strategy to win the tournament final.",
        "audio": "",
        "interval": 0,
        "ease": 2.5,
        "due": 0
    },
    {
        "id": 1818,
        "target": "Necesito unas zapatillas deportivas nuevas para correr la carrera.",
        "english": "I need new running shoes for the race.",
        "audio": "",
        "interval": 0,
        "ease": 2.5,
        "due": 0
    },
    {
        "id": 1819,
        "target": "El surf y el windsurf son deportes acuáticos muy emocionantes.",
        "english": "Surfing and windsurfing are very exciting water sports.",
        "audio": "",
        "interval": 0,
        "ease": 2.5,
        "due": 0
    },
    {
        "id": 1820,
        "target": "Marcó un gol espectacular desde fuera del área.",
        "english": "He scored a spectacular goal from outside the box.",
        "audio": "",
        "interval": 0,
        "ease": 2.5,
        "due": 0,
        "grammar": "\"Es el jugador más rápido que he visto\" — superlative + relative clause: \"el más rápido que he visto\" = the fastest I've seen. Present perfect for life experience."
    },
    {
        "id": 1821,
        "target": "Me encanta dibujar paisajes con lápices de colores y acuarelas.",
        "english": "I love drawing landscapes with colored pencils and watercolors.",
        "audio": "",
        "interval": 0,
        "ease": 2.5,
        "due": 0
    },
    {
        "id": 1822,
        "target": "Mi abuela me enseñó a coser y a tejer cuando era pequeña.",
        "english": "My grandmother taught me to sew and knit when I was little.",
        "audio": "",
        "interval": 0,
        "ease": 2.5,
        "due": 0
    },
    {
        "id": 1823,
        "target": "La jardinería me relaja; planto flores y cuido un pequeño huerto.",
        "english": "Gardening relaxes me; I plant flowers and tend a small vegetable garden.",
        "audio": "",
        "interval": 0,
        "ease": 2.5,
        "due": 0
    },
    {
        "id": 1824,
        "target": "Colecciono sellos de todos los países que he visitado.",
        "english": "I collect stamps from all the countries I have visited.",
        "audio": "",
        "interval": 0,
        "ease": 2.5,
        "due": 0
    },
    {
        "id": 1825,
        "target": "Los viernes por la noche jugamos a juegos de mesa en familia.",
        "english": "On Friday nights we play board games as a family.",
        "audio": "",
        "interval": 0,
        "ease": 2.5,
        "due": 0
    },
    {
        "id": 1826,
        "target": "Los videojuegos pueden mejorar la coordinación y la capacidad de resolver problemas.",
        "english": "Video games can improve coordination and problem-solving ability.",
        "audio": "",
        "interval": 0,
        "ease": 2.5,
        "due": 0
    },
    {
        "id": 1827,
        "target": "Toco la guitarra desde los catorce años y ahora estoy aprendiendo batería.",
        "english": "I've been playing guitar since I was fourteen and now I'm learning drums.",
        "audio": "",
        "interval": 0,
        "ease": 2.5,
        "due": 0
    },
    {
        "id": 1828,
        "target": "La flauta, el violín y el violonchelo son instrumentos de una orquesta clásica.",
        "english": "The flute, violin, and cello are instruments of a classical orchestra.",
        "audio": "",
        "interval": 0,
        "ease": 2.5,
        "due": 0
    },
    {
        "id": 1829,
        "target": "Aprendí a bailar salsa en un curso que dura tres meses.",
        "english": "I learned to dance salsa in a course that lasts three months.",
        "audio": "",
        "interval": 0,
        "ease": 2.5,
        "due": 0
    },
    {
        "id": 1830,
        "target": "La fotografía de naturaleza requiere paciencia y un buen objetivo.",
        "english": "Nature photography requires patience and a good lens.",
        "audio": "",
        "interval": 0,
        "ease": 2.5,
        "due": 0,
        "grammar": "\"Me puse la camiseta roja y los pantalones azules\" — \"ponerse\" (preterite: me puse) for putting on clothes. Color adjectives agree: roja (fem), azules (plural)."
    },
    {
        "id": 1831,
        "target": "Mi camiseta roja es mi favorita; la llevo casi todos los días.",
        "english": "My red t-shirt is my favorite; I wear it almost every day.",
        "audio": "",
        "interval": 0,
        "ease": 2.5,
        "due": 0
    },
    {
        "id": 1832,
        "target": "Necesito comprar calcetines negros y unos guantes para el invierno.",
        "english": "I need to buy black socks and some gloves for winter.",
        "audio": "",
        "interval": 0,
        "ease": 2.5,
        "due": 0
    },
    {
        "id": 1833,
        "target": "Se puso el traje azul oscuro con corbata gris para la entrevista.",
        "english": "He put on the dark blue suit with a gray tie for the interview.",
        "audio": "",
        "interval": 0,
        "ease": 2.5,
        "due": 0
    },
    {
        "id": 1834,
        "target": "La bufanda morada combina muy bien con tu abrigo marrón.",
        "english": "The purple scarf goes very well with your brown coat.",
        "audio": "",
        "interval": 0,
        "ease": 2.5,
        "due": 0
    },
    {
        "id": 1835,
        "target": "Lleva unas botas de cuero negro y un cinturón a juego.",
        "english": "She's wearing black leather boots and a matching belt.",
        "audio": "",
        "interval": 0,
        "ease": 2.5,
        "due": 0
    },
    {
        "id": 1836,
        "target": "La sudadera verde claro es muy cómoda para estar en casa.",
        "english": "The light green hoodie is very comfortable for being at home.",
        "audio": "",
        "interval": 0,
        "ease": 2.5,
        "due": 0
    },
    {
        "id": 1837,
        "target": "¿De qué color prefieres la chaqueta: blanca, naranja o rosa?",
        "english": "What color do you prefer the jacket: white, orange, or pink?",
        "audio": "",
        "interval": 0,
        "ease": 2.5,
        "due": 0
    },
    {
        "id": 1838,
        "target": "Me probé unos pantalones grises pero me quedaban demasiado grandes.",
        "english": "I tried on some gray pants but they were too big for me.",
        "audio": "",
        "interval": 0,
        "ease": 2.5,
        "due": 0
    },
    {
        "id": 1839,
        "target": "El vestido amarillo con flores rojas es perfecto para el verano.",
        "english": "The yellow dress with red flowers is perfect for summer.",
        "audio": "",
        "interval": 0,
        "ease": 2.5,
        "due": 0
    },
    {
        "id": 1840,
        "target": "Los niños pintaron un arcoíris con todos los colores del espectro.",
        "english": "The children painted a rainbow with all the colors of the spectrum.",
        "audio": "",
        "interval": 0,
        "ease": 2.5,
        "due": 0,
        "grammar": "\"Prefiero las películas de acción a las de comedia\" — \"preferir\" (e→ie) + noun + \"a\" + noun = to prefer X over Y. \"Las de comedia\" — \"las\" replaces \"películas.\""
    },
    {
        "id": 1841,
        "target": "El agua del lago era de un azul turquesa intenso y cristalino.",
        "english": "The lake water was an intense and crystalline turquoise blue.",
        "audio": "",
        "interval": 0,
        "ease": 2.5,
        "due": 0
    },
    {
        "id": 1842,
        "target": "Las hojas cambian de verde a amarillo, naranja y rojo en otoño.",
        "english": "The leaves change from green to yellow, orange, and red in autumn.",
        "audio": "",
        "interval": 0,
        "ease": 2.5,
        "due": 0
    },
    {
        "id": 1843,
        "target": "El gato es negro con manchas blancas en las patas y el pecho.",
        "english": "The cat is black with white spots on its paws and chest.",
        "audio": "",
        "interval": 0,
        "ease": 2.5,
        "due": 0
    },
    {
        "id": 1844,
        "target": "Me gusta el color dorado porque me recuerda al atardecer.",
        "english": "I like the color gold because it reminds me of sunset.",
        "audio": "",
        "interval": 0,
        "ease": 2.5,
        "due": 0
    },
    {
        "id": 1845,
        "target": "La pared del salón es blanca pero estamos pensando en pintarla de color crema.",
        "english": "The living room wall is white but we are thinking of painting it cream.",
        "audio": "",
        "interval": 0,
        "ease": 2.5,
        "due": 0
    },
    {
        "id": 1846,
        "target": "El perro es marrón claro con orejas largas y ojos oscuros.",
        "english": "The dog is light brown with long ears and dark eyes.",
        "audio": "",
        "interval": 0,
        "ease": 2.5,
        "due": 0
    },
    {
        "id": 1847,
        "target": "Para el cumpleaños de mi hija compramos globos de todos los colores.",
        "english": "For my daughter's birthday we bought balloons of all colors.",
        "audio": "",
        "interval": 0,
        "ease": 2.5,
        "due": 0
    },
    {
        "id": 1848,
        "target": "¿A qué hora abren los gimnasios por la mañana en esta ciudad?",
        "english": "What time do gyms open in the morning in this city?",
        "audio": "",
        "interval": 0,
        "ease": 2.5,
        "due": 0
    },
    {
        "id": 1849,
        "target": "Hago pesas y abdominales tres días a la semana en el gimnasio.",
        "english": "I do weights and sit-ups three days a week at the gym.",
        "audio": "",
        "interval": 0,
        "ease": 2.5,
        "due": 0
    },
    {
        "id": 1850,
        "target": "Después del entrenamiento, estiro durante quince minutos para evitar lesiones.",
        "english": "After training, I stretch for fifteen minutes to avoid injuries.",
        "audio": "",
        "interval": 0,
        "ease": 2.5,
        "due": 0,
        "grammar": "\"Ojalá nuestro equipo gane el campeonato\" — \"ojalá\" + present subjunctive for a wish about a possible future event. \"Gane\" = subjunctive of \"ganar.\""
    },
    {
        "id": 1851,
        "target": "Las artes marciales enseñan disciplina, respeto y autodefensa.",
        "english": "Martial arts teach discipline, respect, and self-defense.",
        "audio": "",
        "interval": 0,
        "ease": 2.5,
        "due": 0
    },
    {
        "id": 1852,
        "target": "El patinaje sobre hielo es un deporte elegante y exigente a la vez.",
        "english": "Ice skating is both an elegant and demanding sport.",
        "audio": "",
        "interval": 0,
        "ease": 2.5,
        "due": 0
    },
    {
        "id": 1853,
        "target": "Nos encanta acampar en el bosque y hacer fogatas por la noche.",
        "english": "We love camping in the forest and making bonfires at night.",
        "audio": "",
        "interval": 0,
        "ease": 2.5,
        "due": 0
    },
    {
        "id": 1854,
        "target": "La pesca con caña es una actividad muy relajante junto al río.",
        "english": "Rod fishing is a very relaxing activity by the river.",
        "audio": "",
        "interval": 0,
        "ease": 2.5,
        "due": 0
    },
    {
        "id": 1855,
        "target": "¿Prefieres ver el partido en el estadio o por televisión?",
        "english": "Do you prefer to watch the match at the stadium or on television?",
        "audio": "",
        "interval": 0,
        "ease": 2.5,
        "due": 0
    },
    {
        "id": 1856,
        "target": "El ajedrez es un juego de estrategia que ejercita la mente.",
        "english": "Chess is a strategy game that exercises the mind.",
        "audio": "",
        "interval": 0,
        "ease": 2.5,
        "due": 0
    },
    {
        "id": 1857,
        "target": "Los rompecabezas de mil piezas me ayudan a desconectar del estrés.",
        "english": "Thousand-piece puzzles help me disconnect from stress.",
        "audio": "",
        "interval": 0,
        "ease": 2.5,
        "due": 0
    },
    {
        "id": 1858,
        "target": "Hago cerámica en un taller los sábados por la mañana.",
        "english": "I do ceramics at a workshop on Saturday mornings.",
        "audio": "",
        "interval": 0,
        "ease": 2.5,
        "due": 0
    },
    {
        "id": 1859,
        "target": "El club de lectura se reúne una vez al mes para comentar una novela.",
        "english": "The book club meets once a month to discuss a novel.",
        "audio": "",
        "interval": 0,
        "ease": 2.5,
        "due": 0
    },
    {
        "id": 1860,
        "target": "Me he apuntado a un curso de cocina italiana los miércoles por la tarde.",
        "english": "I've signed up for an Italian cooking course on Wednesday afternoons.",
        "audio": "",
        "interval": 0,
        "ease": 2.5,
        "due": 0,
        "grammar": "\"Mientras unos nadan, otros toman el sol\" — \"mientras\" + present for simultaneous habitual actions. \"Unos...otros\" = some...others."
    },
    {
        "id": 1861,
        "target": "El boxeo es un deporte que requiere rapidez, resistencia y técnica.",
        "english": "Boxing is a sport that requires speed, endurance, and technique.",
        "audio": "",
        "interval": 0,
        "ease": 2.5,
        "due": 0
    },
    {
        "id": 1862,
        "target": "El golf se juega en un campo con dieciocho hoyos.",
        "english": "Golf is played on a course with eighteen holes.",
        "audio": "",
        "interval": 0,
        "ease": 2.5,
        "due": 0
    },
    {
        "id": 1863,
        "target": "Alquilamos una canoa y remamos por el río durante toda la tarde.",
        "english": "We rented a canoe and paddled down the river all afternoon.",
        "audio": "",
        "interval": 0,
        "ease": 2.5,
        "due": 0
    },
    {
        "id": 1864,
        "target": "El equipo de béisbol necesita un bate, un guante y una pelota.",
        "english": "The baseball team needs a bat, a glove, and a ball.",
        "audio": "",
        "interval": 0,
        "ease": 2.5,
        "due": 0
    },
    {
        "id": 1865,
        "target": "La gimnasia rítmica combina movimientos acrobáticos con música.",
        "english": "Rhythmic gymnastics combines acrobatic movements with music.",
        "audio": "",
        "interval": 0,
        "ease": 2.5,
        "due": 0
    },
    {
        "id": 1866,
        "target": "La liga de fútbol tiene veinte equipos que compiten durante toda la temporada.",
        "english": "The soccer league has twenty teams that compete throughout the season.",
        "audio": "",
        "interval": 0,
        "ease": 2.5,
        "due": 0
    },
    {
        "id": 1867,
        "target": "Ganó la medalla de oro en los cien metros lisos con un tiempo récord.",
        "english": "He won the gold medal in the hundred-meter dash with a record time.",
        "audio": "",
        "interval": 0,
        "ease": 2.5,
        "due": 0
    },
    {
        "id": 1868,
        "target": "El dopaje en el deporte es una práctica deshonesta que se castiga con la descalificación.",
        "english": "Doping in sport is a dishonest practice that is punished with disqualification.",
        "audio": "",
        "interval": 0,
        "ease": 2.5,
        "due": 0
    },
    {
        "id": 1869,
        "target": "Mi hermano colecciona cómics antiguos y ya tiene más de trescientos.",
        "english": "My brother collects old comics and already has more than three hundred.",
        "audio": "",
        "interval": 0,
        "ease": 2.5,
        "due": 0
    },
    {
        "id": 1870,
        "target": "Dedico al menos una hora al día a leer antes de dormir.",
        "english": "I dedicate at least one hour a day to reading before bed.",
        "audio": "",
        "interval": 0,
        "ease": 2.5,
        "due": 0,
        "grammar": "\"Se necesitan dos equipos de once jugadores cada uno\" — \"se necesitan\" (passive se, plural agreement). \"Cada uno\" = each one (invariable)."
    },
    {
        "id": 1871,
        "target": "Me relaja escuchar música clásica mientras trabajo o estudio.",
        "english": "Listening to classical music while working or studying relaxes me.",
        "audio": "",
        "interval": 0,
        "ease": 2.5,
        "due": 0
    },
    {
        "id": 1872,
        "target": "Los podcasts de historia son los que más me gustan.",
        "english": "History podcasts are the ones I like the most.",
        "audio": "",
        "interval": 0,
        "ease": 2.5,
        "due": 0
    },
    {
        "id": 1873,
        "target": "El bricolaje es un pasatiempo útil: puedes arreglar cosas en casa.",
        "english": "DIY is a useful hobby: you can fix things around the house.",
        "audio": "",
        "interval": 0,
        "ease": 2.5,
        "due": 0
    },
    {
        "id": 1874,
        "target": "Aprendí a tocar el ukelele viendo tutoriales en internet.",
        "english": "I learned to play the ukulele by watching tutorials on the internet.",
        "audio": "",
        "interval": 0,
        "ease": 2.5,
        "due": 0
    },
    {
        "id": 1875,
        "target": "El karaoke es una actividad divertida para hacer con amigos.",
        "english": "Karaoke is a fun activity to do with friends.",
        "audio": "",
        "interval": 0,
        "ease": 2.5,
        "due": 0
    },
    {
        "id": 1876,
        "target": "Pintamos las paredes de la habitación de un color azul celeste muy bonito.",
        "english": "We painted the bedroom walls a very pretty sky blue color.",
        "audio": "",
        "interval": 0,
        "ease": 2.5,
        "due": 0
    },
    {
        "id": 1877,
        "target": "El rojo simboliza pasión en muchas culturas, mientras que el blanco representa pureza.",
        "english": "Red symbolizes passion in many cultures, while white represents purity.",
        "audio": "",
        "interval": 0,
        "ease": 2.5,
        "due": 0
    },
    {
        "id": 1878,
        "target": "Las flores del jardín son de color lila, rosa y blanco.",
        "english": "The garden flowers are lilac, pink, and white.",
        "audio": "",
        "interval": 0,
        "ease": 2.5,
        "due": 0
    },
    {
        "id": 1879,
        "target": "El cielo al amanecer se tiñe de tonos rosados, anaranjados y violetas.",
        "english": "The sky at dawn is tinted with pink, orange, and violet tones.",
        "audio": "",
        "interval": 0,
        "ease": 2.5,
        "due": 0
    },
    {
        "id": 1880,
        "target": "¿Has probado alguna vez la escalada en un rocódromo cubierto?",
        "english": "Have you ever tried climbing at an indoor climbing wall?",
        "audio": "",
        "interval": 0,
        "ease": 2.5,
        "due": 0,
        "grammar": "\"Me gustaría aprender a pintar al óleo\" — conditional \"gustaría\" for wishes. \"Aprender a\" + infinitive. \"Al óleo\" = in oils (art technique)."
    },
    {
        "id": 1881,
        "target": "El campamento de verano incluye actividades como tiro con arco y piragüismo.",
        "english": "The summer camp includes activities like archery and canoeing.",
        "audio": "",
        "interval": 0,
        "ease": 2.5,
        "due": 0
    },
    {
        "id": 1882,
        "target": "Mi pasatiempo favorito es ver documentales sobre ciencia y naturaleza.",
        "english": "My favorite hobby is watching documentaries about science and nature.",
        "audio": "",
        "interval": 0,
        "ease": 2.5,
        "due": 0
    },
    {
        "id": 1883,
        "target": "El equipo femenino de balonmano ganó el campeonato europeo.",
        "english": "The women's handball team won the European championship.",
        "audio": "",
        "interval": 0,
        "ease": 2.5,
        "due": 0
    },
    {
        "id": 1884,
        "target": "La esgrima es un deporte olímpico que combina velocidad y precisión.",
        "english": "Fencing is an Olympic sport that combines speed and precision.",
        "audio": "",
        "interval": 0,
        "ease": 2.5,
        "due": 0
    },
    {
        "id": 1885,
        "target": "Compramos un juego de pinturas al óleo para el taller de arte.",
        "english": "We bought a set of oil paints for the art workshop.",
        "audio": "",
        "interval": 0,
        "ease": 2.5,
        "due": 0
    },
    {
        "id": 1886,
        "target": "El triatlón combina natación, ciclismo y carrera a pie en una sola prueba.",
        "english": "Triathlon combines swimming, cycling, and running in a single event.",
        "audio": "",
        "interval": 0,
        "ease": 2.5,
        "due": 0
    },
    {
        "id": 1887,
        "target": "Los deportes de invierno como el snowboard atraen a miles de turistas a la sierra.",
        "english": "Winter sports like snowboarding attract thousands of tourists to the mountains.",
        "audio": "",
        "interval": 0,
        "ease": 2.5,
        "due": 0
    },
    {
        "id": 1888,
        "target": "Hacemos rutas en bicicleta por caminos rurales los domingos por la mañana.",
        "english": "We go on bike rides along country roads on Sunday mornings.",
        "audio": "",
        "interval": 0,
        "ease": 2.5,
        "due": 0
    },
    {
        "id": 1889,
        "target": "El ajedrez en línea me permite jugar contra personas de todo el mundo.",
        "english": "Online chess allows me to play against people from all over the world.",
        "audio": "",
        "interval": 0,
        "ease": 2.5,
        "due": 0
    },
    {
        "id": 1890,
        "target": "La capoeira es un arte marcial brasileño que mezcla danza, acrobacia y música.",
        "english": "Capoeira is a Brazilian martial art that mixes dance, acrobatics, and music.",
        "audio": "",
        "interval": 0,
        "ease": 2.5,
        "due": 0,
        "grammar": "\"Cuanto más practicas, mejor juegas\" — \"cuanto más...mejor\" = the more...the better. Present tense for general truths. \"Juegas\" — jugar (u→ue)."
    },
    {
        "id": 1891,
        "target": "El paracaidismo es una experiencia única pero hay que tener valor para saltar.",
        "english": "Skydiving is a unique experience but you need courage to jump.",
        "audio": "",
        "interval": 0,
        "ease": 2.5,
        "due": 0
    },
    {
        "id": 1892,
        "target": "Monté a caballo por primera vez durante unas vacaciones en el campo.",
        "english": "I rode a horse for the first time during a vacation in the countryside.",
        "audio": "",
        "interval": 0,
        "ease": 2.5,
        "due": 0
    },
    {
        "id": 1893,
        "target": "La vela es un deporte que depende mucho del viento y de la habilidad del navegante.",
        "english": "Sailing is a sport that depends a lot on the wind and the sailor's skill.",
        "audio": "",
        "interval": 0,
        "ease": 2.5,
        "due": 0
    },
    {
        "id": 1894,
        "target": "El buceo me permitió ver corales, peces tropicales y tortugas marinas.",
        "english": "Scuba diving allowed me to see corals, tropical fish, and sea turtles.",
        "audio": "",
        "interval": 0,
        "ease": 2.5,
        "due": 0
    },
    {
        "id": 1895,
        "target": "Los aficionados al modelismo construyen maquetas de trenes, aviones y barcos.",
        "english": "Model-making enthusiasts build scale models of trains, planes, and ships.",
        "audio": "",
        "interval": 0,
        "ease": 2.5,
        "due": 0
    },
    {
        "id": 1896,
        "target": "Organicé una noche de cine en casa con palomitas y refrescos.",
        "english": "I organized a movie night at home with popcorn and soft drinks.",
        "audio": "",
        "interval": 0,
        "ease": 2.5,
        "due": 0
    },
    {
        "id": 1897,
        "target": "El deporte fomenta valores como el trabajo en equipo, la superación y el respeto.",
        "english": "Sports foster values like teamwork, self-improvement, and respect.",
        "audio": "",
        "interval": 0,
        "ease": 2.5,
        "due": 0
    },
    {
        "id": 1898,
        "target": "Los juegos de rol estimulan la creatividad y la capacidad narrativa.",
        "english": "Role-playing games stimulate creativity and narrative ability.",
        "audio": "",
        "interval": 0,
        "ease": 2.5,
        "due": 0
    },
    {
        "id": 1899,
        "target": "Cultivar un pasatiempo enriquece la vida y ayuda a mantener el equilibrio emocional.",
        "english": "Cultivating a hobby enriches life and helps maintain emotional balance.",
        "audio": "",
        "interval": 0,
        "ease": 2.5,
        "due": 0
    },
    {
        "id": 1900,
        "target": "Ya sea un deporte, un arte o un juego, lo importante es disfrutar del proceso.",
        "english": "Whether it's a sport, an art, or a game, what matters is enjoying the process.",
        "audio": "",
        "interval": 0,
        "ease": 2.5,
        "due": 0
    }
]
